simc/__init__.py
simc/compiler.py
simc/global_helpers.py
simc/lexical_analyzer.py
simc/op_code.py
simc/package-index
simc/simc.py
simc/simpack.py
simc/symbol_table.py
simc/token_class.py
simc/parser/__init__.py
simc/parser/array_parser.py
simc/parser/conditional_parser.py
simc/parser/function_parser.py
simc/parser/loop_parser.py
simc/parser/parser_constants.py
simc/parser/simc_parser.py
simc/parser/struct_parser.py
simc/parser/variable_parser.py
simc-0.1a4.dist-info/LICENSE
simc-0.1a4.dist-info/METADATA
simc-0.1a4.dist-info/WHEEL
simc-0.1a4.dist-info/entry_points.txt
simc-0.1a4.dist-info/top_level.txt
simc-0.1a4.dist-info/RECORD
