Metadata-Version: 2.1
Name: simc
Version: 0.1a4
Summary: A dynamically typed high-level front end for C
Home-page: https://github.com/cimplec/simc
Author: Siddhartha Dhar Choudhury
Author-email: sdharchou@gmail.com
License: GNU General Public License v3
Platform: UNKNOWN
Classifier: License :: OSI Approved :: GNU General Public License v3 (GPLv3)
Classifier: Programming Language :: Python :: 3
Classifier: Programming Language :: Python :: 3.9
Classifier: Programming Language :: Python :: 3.8
Classifier: Programming Language :: Python :: 3.7
Classifier: Programming Language :: Python :: 3.6
Requires-Dist: requests
